{
  "negativePlural": [
    {"sentence": "many students on the roof."},
    {"sentence": "many stars in the sky."},
    {"sentence": "many people at the airport."},
    {"sentence": "any bikes on the bus."},
    {"sentence": "many students in the class."},
    {"sentence": "many children at the playground."},
    {"sentence": "any pens on the moon."},
    {"sentence": "any glasses in the shower."},
    {"sentence": "many buses on the road."},
    {"sentence": "many trees on the bus."},
    {"sentence": "many students in the cafeteria."},
    {"sentence": "any pens in the bag."},
    {"sentence": "many students in the classroom."},
    {"sentence": "any flowers in the elevator."},
    {"sentence": "any chairs in the pool."},
    {"sentence": "any flowers in the car."},
    {"sentence": "many shops open today."},
    {"sentence": "many shops in the mall."},
    {"sentence": "many cars in the street."},
    {"sentence": "any plates in the sink."},
    {"sentence": "many people in the refrigerator."},
    {"sentence": "many cars in the sky."},
    {"sentence": "many shops in the ocean."},
    {"sentence": "many people at the cinema."},
    {"sentence": "any fish on the roof."},
    {"sentence": "any books on the shelf."},
    {"sentence": "any pens in the case."},
    {"sentence": "many children in the museum."},
    {"sentence": "any cups in the cupboard."},
    {"sentence": "any books on the floor."},
    {"sentence": "any apples in the bowl."},
    {"sentence": "any chairs on the roof."},
    {"sentence": "any eggs in the basket."},
    {"sentence": "any bananas on the table."},
    {"sentence": "any bikes near the school."},
    {"sentence": "many trees on the mountain."},
    {"sentence": "any plates on the shelf."},
    {"sentence": "any plates on the counter."},
    {"sentence": "any bikes in the swimming pool."},
    {"sentence": "any chairs in the elevator."},
    {"sentence": "many birds in the car."},
    {"sentence": "many students on the moon."},
    {"sentence": "many trees in the neighborhood."},
    {"sentence": "many birds in the cage."},
    {"sentence": "any apples in the basket."},
    {"sentence": "many trees in the desert."},
    {"sentence": "many students in the gym."},
    {"sentence": "many shops in the village."},
    {"sentence": "any apples in the fridge."},
    {"sentence": "many trees on the moon."},
    {"sentence": "many clouds inside the room."},
    {"sentence": "any eggs in the fridge."},
    {"sentence": "any pens in the tree."},
    {"sentence": "any books in the suitcase."},
    {"sentence": "many people in the sky."},
    {"sentence": "many clouds in the kitchen."},
    {"sentence": "any pens on the desk."},
    {"sentence": "many cars at the beach."},
    {"sentence": "any plates on the floor."},
    {"sentence": "any eggs on the counter."},
    {"sentence": "any pens in the swimming pool."},
    {"sentence": "many trees in the pool."},
    {"sentence": "any fish in the lake."},
    {"sentence": "any eggs on the bus."},
    {"sentence": "many children in the washing machine."},
    {"sentence": "any pens in the ocean."},
    {"sentence": "any eggs in the carton."},
    {"sentence": "any toys in the bathtub."},
    {"sentence": "many restaurants in this area."},
    {"sentence": "any flowers in the refrigerator."},
    {"sentence": "any bananas in the car."},
    {"sentence": "any shoes under the bed."},
    {"sentence": "many people in the closet."},
    {"sentence": "many trees on this street."},
    {"sentence": "any books in the fridge."},
    {"sentence": "many people in the bathtub."},
    {"sentence": "any oranges in the fridge."},
    {"sentence": "any fish in the pond."},
    {"sentence": "any pens in the drawer."},
    {"sentence": "any bikes in the garage."},
    {"sentence": "many clouds in the sky."},
    {"sentence": "any birds in the sky."},
    {"sentence": "any planes in the sky."},
    {"sentence": "many restaurants in this town."},
    {"sentence": "many restaurants on the moon."},
    {"sentence": "any cars in the garage."},
    {"sentence": "any toys in the dishwasher."},
    {"sentence": "any plates in the picnic basket."},
    {"sentence": "any toys in the box."},
    {"sentence": "many students in the ocean."},
    {"sentence": "any chairs on the porch."},
    {"sentence": "any chairs in the soup."},
    {"sentence": "any fish in the car."},
    {"sentence": "many shops in this village."},
    {"sentence": "many students in the washing machine."},
    {"sentence": "any toys in the ocean."},
    {"sentence": "any plates on the table."},
    {"sentence": "many people in the elevator."},
    {"sentence": "many trees in the park."},
    {"sentence": "many shops in the elevator."},
    {"sentence": "any toys in the office."},
    {"sentence": "any pens in the vase."},
    {"sentence": "any glasses on the table."},
    {"sentence": "many people on the moon."},
    {"sentence": "any flowers in the vase."},
    {"sentence": "many people on the computer."},
    {"sentence": "many cars in the ocean."},
    {"sentence": "any apples in the car."},
    {"sentence": "many students on the bus."},
    {"sentence": "many trees on the street."},
    {"sentence": "many birds in the elevator."},
    {"sentence": "any toys on the moon."},
    {"sentence": "any plates in the cupboard."},
    {"sentence": "many people in the swimming pool."},
    {"sentence": "many birds on the ceiling."},
    {"sentence": "many cars on the ceiling."},
    {"sentence": "any toys on the ceiling."},
    {"sentence": "many people in the mailbox."},
    {"sentence": "many birds in the sky."},
    {"sentence": "many cars on the road."},
    {"sentence": "many people on the ceiling."},
    {"sentence": "many students in the elevator."},
    {"sentence": "any chairs in the room."},
    {"sentence": "any books on the moon."},
    {"sentence": "many buildings in this area."},
    {"sentence": "many cars in the tunnel."},
    {"sentence": "many people in the oven."},
    {"sentence": "any trees in the yard."},
    {"sentence": "many people at the park."},
    {"sentence": "any chairs in the sky."},
    {"sentence": "many shops in this town."},
    {"sentence": "any books on the table."},
    {"sentence": "many people at the beach."},
    {"sentence": "any toys in the oven."},
    {"sentence": "any glasses in the cupboard."},
    {"sentence": "many students in the class today."},
    {"sentence": "many cars in the kitchen."},
    {"sentence": "any toys in the car."},
    {"sentence": "any pens on the floor."},
    {"sentence": "many people at the theater."},
    {"sentence": "any apples on the tree."},
    {"sentence": "any pens in the soup."},
    {"sentence": "many people in the library."},
    {"sentence": "many birds in the house."},
    {"sentence": "any chairs by the window."},
    {"sentence": "any books in the bathtub."},
    {"sentence": "any glasses on the shelf."},
    {"sentence": "any apples on the computer."},
    {"sentence": "many restaurants on this road."},
    {"sentence": "any apples in the pie."},
    {"sentence": "many shops at the airport."},
    {"sentence": "many people in the gym."},
    {"sentence": "many people on the beach."},
    {"sentence": "any plates in the tree."},
    {"sentence": "many people at the gym."},
    {"sentence": "any chairs around the table."},
    {"sentence": "many books in the library."},
    {"sentence": "many fish in the pond."},
    {"sentence": "many restaurants in the forest."},
    {"sentence": "any plates in the sky."},
    {"sentence": "any flowers on the computer."},
    {"sentence": "many people at the beach today."},
    {"sentence": "any flowers on the windowsill."},
    {"sentence": "any plates on the ceiling."},
    {"sentence": "many trees in the city center."},
    {"sentence": "many buildings underwater."},
    {"sentence": "any chairs in this room."},
    {"sentence": "many children at the party."},
    {"sentence": "many people at the museum."},
    {"sentence": "many trees in the bathroom."},
    {"sentence": "any pencils in the case."},
    {"sentence": "any apples in the shoe."},
    {"sentence": "many cars in the parking lot."},
    {"sentence": "many people at the restaurant."},
    {"sentence": "any flowers in the office."},
    {"sentence": "any toys on the floor."},
    {"sentence": "many trees in the oven."},
    {"sentence": "any chairs on the bus."},
    {"sentence": "any eggs on the plate."},
    {"sentence": "many cars on the highway."},
    {"sentence": "any eggs in the bookcase."},
    {"sentence": "any books on the ceiling."},
    {"sentence": "any chairs in the tree."},
    {"sentence": "any fish in the sky."},
    {"sentence": "any toys on the shelf."},
    {"sentence": "many clouds in the sky today."},
    {"sentence": "any bananas in the bowl."},
    {"sentence": "many birds in the tree."},
    {"sentence": "any plates in the garden."},
    {"sentence": "many trees in the elevator."},
    {"sentence": "many students in the library."},
    {"sentence": "many buildings in the forest."},
    {"sentence": "many buildings on this street."},
    {"sentence": "many people on the roof."},
    {"sentence": "any flowers in the garden."},
    {"sentence": "many cars in the bathtub."},
    {"sentence": "any glasses on the moon."},
    {"sentence": "any fish in the bathtub."},
    {"sentence": "many trees in the car."},
    {"sentence": "many people at the station."},
    {"sentence": "many trees in the yard."},
    {"sentence": "many shops in the bathroom."},
    {"sentence": "any fish in the aquarium."}
  ],
  "negativeSingular": [
    {"sentence": "any ash in the fireplace."},
    {"sentence": "a tree in front of the house."},
    {"sentence": "any talent in the musician."},
    {"sentence": "a poster in the bathroom."},
    {"sentence": "a map on the wall."},
    {"sentence": "any music in the concert."},
    {"sentence": "any calm in the morning."},
    {"sentence": "a bus in the bus lane."},
    {"sentence": "a poster on the wall."},
    {"sentence": "any echo in the tunnel."},
    {"sentence": "a lamp on the beach."},
    {"sentence": "a computer in the garden."},
    {"sentence": "a clock in the kitchen."},
    {"sentence": "any dryness in the desert."},
    {"sentence": "a dog on the table."},
    {"sentence": "a TV in the car."},
    {"sentence": "a poster in the refrigerator."},
    {"sentence": "a clock in the tree."},
    {"sentence": "a teacher in the cafeteria."},
    {"sentence": "a chair in the attic."},
    {"sentence": "a car on the roof."},
    {"sentence": "a chair by the window."},
    {"sentence": "any snow in the mountains."},
    {"sentence": "any sand on the beach."},
    {"sentence": "a plant on the windowsill."},
    {"sentence": "a picture on this wall."},
    {"sentence": "any faith in the belief."},
    {"sentence": "a lamp in the dining room."},
    {"sentence": "a computer in this office."},
    {"sentence": "a window in this room."},
    {"sentence": "a TV in the restaurant."},
    {"sentence": "a phone in the swimming pool."},
    {"sentence": "a lamp in the corner."},
    {"sentence": "any chatter in the cafeteria."},
    {"sentence": "a picture under the carpet."},
    {"sentence": "any information on the internet."},
    {"sentence": "a mirror in the dishwasher."},
    {"sentence": "a chair at the table."},
    {"sentence": "a bus on the street."},
    {"sentence": "any surprise in the party."},
    {"sentence": "any light in the hallway."},
    {"sentence": "a clock in this room."},
    {"sentence": "a lamp on the bookshelf."},
    {"sentence": "any mist in the morning."},
    {"sentence": "any mystery in the novel."},
    {"sentence": "any truth in the statement."},
    {"sentence": "a cat in the room."},
    {"sentence": "a bus on the road."},
    {"sentence": "any joy in the celebration."},
    {"sentence": "any wind in the air."},
    {"sentence": "any energy in the crowd."},
    {"sentence": "any skill in the craftsman."},
    {"sentence": "a bird in the tree."},
    {"sentence": "a cat in the oven."},
    {"sentence": "a cat in the sky."},
    {"sentence": "a book under the bed."},
    {"sentence": "a bus in the bedroom."},
    {"sentence": "any power in the engine."},
    {"sentence": "a TV in the kitchen."},
    {"sentence": "a cup in the bedroom."},
    {"sentence": "any flour in the bowl."},
    {"sentence": "a computer on the roof."},
    {"sentence": "a bus at the stop."},
    {"sentence": "any intelligence in the student."},
    {"sentence": "any meat in the stew."},
    {"sentence": "any noise in the city."},
    {"sentence": "a car in the swimming pool."},
    {"sentence": "a dog in the park."},
    {"sentence": "a teacher on the roof."},
    {"sentence": "any fog in the valley."},
    {"sentence": "a tree near the house."},
    {"sentence": "a TV on the beach."},
    {"sentence": "a dog in the microwave."},
    {"sentence": "a ball in the garden."},
    {"sentence": "a tree in the swimming pool."},
    {"sentence": "a teacher in the closet."},
    {"sentence": "a plant in the car."},
    {"sentence": "a book in the backpack."},
    {"sentence": "any tension in the room."},
    {"sentence": "any chocolate in the cake."},
    {"sentence": "a TV in the forest."},
    {"sentence": "a lamp on the table."},
    {"sentence": "a cat in the washing machine."},
    {"sentence": "any coffee in the cup."},
    {"sentence": "any steam in the shower."},
    {"sentence": "a clock on the wall."},
    {"sentence": "any shadow under the tree."},
    {"sentence": "a bus in the swimming pool."},
    {"sentence": "any cold in the winter."},
    {"sentence": "a phone in the tree."},
    {"sentence": "a lamp on the desk."},
    {"sentence": "a computer in the bedroom."},
    {"sentence": "a door to the bathroom."},
    {"sentence": "a computer on the table."},
    {"sentence": "a cat on the bus."},
    {"sentence": "any pollen in the air."},
    {"sentence": "a clock on the shelf."},
    {"sentence": "a TV in the bedroom."},
    {"sentence": "a cat on the sofa."},
    {"sentence": "a cat in the yard."},
    {"sentence": "a lamp on the bus."},
    {"sentence": "any salad in the bowl."},
    {"sentence": "a clock on the computer."},
    {"sentence": "a cat in the umbrella."},
    {"sentence": "a cup in the sink."},
    {"sentence": "a picture in the newspaper."},
    {"sentence": "any pasta in the pot."},
    {"sentence": "a chair in the sink."},
    {"sentence": "a book on the TV."},
    {"sentence": "a cup in the mailbox."},
    {"sentence": "any research in the university."},
    {"sentence": "a phone in the bedroom."},
    {"sentence": "any sound in the headphones."},
    {"sentence": "a TV in the mailbox."},
    {"sentence": "a bus in the living room."},
    {"sentence": "any jam in the jar."},
    {"sentence": "a phone in the bathroom."},
    {"sentence": "any beauty in the nature."},
    {"sentence": "a clock in the refrigerator."},
    {"sentence": "a cat under the bed."},
    {"sentence": "any snow on the ground."},
    {"sentence": "a clock on the beach."},
    {"sentence": "a boy in the playground."},
    {"sentence": "a lamp on the nightstand."},
    {"sentence": "a bus in the garage."},
    {"sentence": "a computer in the kitchen."},
    {"sentence": "any patience in the teacher."},
    {"sentence": "a picture in the soup."},
    {"sentence": "any flour on the counter."},
    {"sentence": "any milk in the fridge."},
    {"sentence": "a picture in the swimming pool."},
    {"sentence": "a cake on the table."},
    {"sentence": "any silence in the library."},
    {"sentence": "a cup on the moon."},
    {"sentence": "a computer in the tree."},
    {"sentence": "a cup in the sky."},
    {"sentence": "a teacher in the refrigerator."},
    {"sentence": "any love in the heart."},
    {"sentence": "a cat in the ocean."},
    {"sentence": "a cat in the car."},
    {"sentence": "a cat on the roof."},
    {"sentence": "a plant in the refrigerator."},
    {"sentence": "a teacher in the room."},
    {"sentence": "any mud on the road."},
    {"sentence": "a cup on the nightstand."},
    {"sentence": "any sadness in the movie."},
    {"sentence": "a cup in the dishwasher."},
    {"sentence": "any sugar on the table."},
    {"sentence": "a phone in the classroom."},
    {"sentence": "a TV in the basement."},
    {"sentence": "a picture on the wall."},
    {"sentence": "any wisdom in the elder."},
    {"sentence": "a cup on the roof."},
    {"sentence": "a computer in the bathtub."},
    {"sentence": "a clock in the office."},
    {"sentence": "any dedication in the volunteer."},
    {"sentence": "any dirt on the shoes."},
    {"sentence": "any warmth in the room."},
    {"sentence": "a picture above the fireplace."},
    {"sentence": "any friendship in the school."},
    {"sentence": "a chair in the tree."},
    {"sentence": "any rice in the pot."},
    {"sentence": "any kindness in the gesture."},
    {"sentence": "a phone on the table."},
    {"sentence": "any bravery in the firefighter."},
    {"sentence": "a key under the mat."},
    {"sentence": "a boat on the lake."},
    {"sentence": "a teacher on the playground."},
    {"sentence": "a TV in the office."},
    {"sentence": "a TV in the living room."},
    {"sentence": "a dog in the refrigerator."},
    {"sentence": "any dust on the shelf."},
    {"sentence": "any heat in the summer."},
    {"sentence": "any history in the museum."},
    {"sentence": "a dog in the elevator."},
    {"sentence": "a computer in the living room."},
    {"sentence": "a phone on the beach."},
    {"sentence": "a dog in the yard."},
    {"sentence": "a lamp in the garage."},
    {"sentence": "any dew on the grass."},
    {"sentence": "a cup on the table."},
    {"sentence": "any oil in the pan."},
    {"sentence": "a phone in the oven."},
    {"sentence": "any grass on the field."},
    {"sentence": "a dog in the store."},
    {"sentence": "a lamp in the soup."},
    {"sentence": "a phone on the shelf."},
    {"sentence": "a teacher in the classroom."},
    {"sentence": "a cat in the bathroom."},
    {"sentence": "any hope in the future."},
    {"sentence": "a bus on the roof."},
    {"sentence": "a dog on the ceiling."},
    {"sentence": "a lamp in the dishwasher."},
    {"sentence": "a phone in the soup."},
    {"sentence": "a dog in the house."},
    {"sentence": "a mirror in the tree."},
    {"sentence": "a cat in the box."},
    {"sentence": "a plant in the office."},
    {"sentence": "any juice in the glass."},
    {"sentence": "a bus stop near my house."},
    {"sentence": "a mirror in the bedroom."},
    {"sentence": "a cup on the shelf."},
    {"sentence": "any speed in the race."},
    {"sentence": "any sunlight in the room."},
    {"sentence": "a clock in the garden."},
    {"sentence": "a poster in the room."},
    {"sentence": "a hat on the hook."},
    {"sentence": "a cup on the desk."},
    {"sentence": "a computer in the classroom."},
    {"sentence": "any rain outside."},
    {"sentence": "any art in the gallery."},
    {"sentence": "a pen on the desk."},
    {"sentence": "a book on the chair."},
    {"sentence": "a clock on the fridge."},
    {"sentence": "a phone in the living room."},
    {"sentence": "a dog in the soup."},
    {"sentence": "any science in the lab."},
    {"sentence": "a car in the garage."},
    {"sentence": "a bus in the kitchen."},
    {"sentence": "a clock in the ocean."},
    {"sentence": "any agility in the athlete."},
    {"sentence": "a book on the ceiling."},
    {"sentence": "any cheese in the sandwich."},
    {"sentence": "any honey on the toast."},
    {"sentence": "any care in the nursing home."},
    {"sentence": "a TV in the tree."},
    {"sentence": "a picture on the bus."},
    {"sentence": "any creativity in the artist."},
    {"sentence": "any fish in the aquarium."},
    {"sentence": "any laughter in the park."},
    {"sentence": "a book in the microwave."},
    {"sentence": "a picture on the ceiling."},
    {"sentence": "a phone in the kitchen."},
    {"sentence": "any peace in the countryside."},
    {"sentence": "a phone on the desk."},
    {"sentence": "a computer on the coffee table."},
    {"sentence": "a mirror in the hallway."},
    {"sentence": "any darkness in the cave."},
    {"sentence": "any clay in the garden."},
    {"sentence": "a car in the driveway."},
    {"sentence": "a dog on the balcony."},
    {"sentence": "any tea in the teapot."},
    {"sentence": "a light in the bathroom."},
    {"sentence": "a picture in the frame."},
    {"sentence": "any smoke from the fire."},
    {"sentence": "a computer on the beach."},
    {"sentence": "any water in the bottle."},
    {"sentence": "a chair on the ceiling."},
    {"sentence": "a mirror in the bathroom."},
    {"sentence": "a clock in the car."},
    {"sentence": "a computer on the desk."},
    {"sentence": "a tree in the elevator."},
    {"sentence": "a dog on the roof."},
    {"sentence": "a cat in the dishwasher."},
    {"sentence": "any smoke in the chimney."},
    {"sentence": "any vibration from the phone."},
    {"sentence": "any soup in the bowl."},
    {"sentence": "a lamp in the swimming pool."},
    {"sentence": "any excitement in the stadium."},
    {"sentence": "a mirror in the kitchen."},
    {"sentence": "a tree in the backyard."},
    {"sentence": "a clock in the shower."},
    {"sentence": "a book in the swimming pool."},
    {"sentence": "a lamp in the bedroom."},
    {"sentence": "any humidity in the tropics."},
    {"sentence": "a mirror in this room."},
    {"sentence": "a chair in the ocean."},
    {"sentence": "a dog in the car."},
    {"sentence": "a tree on the computer."},
    {"sentence": "any salt in the soup."},
    {"sentence": "any flexibility in the gymnast."},
    {"sentence": "a cat in the garden."},
    {"sentence": "a cat on the computer."},
    {"sentence": "a lamp in the refrigerator."},
    {"sentence": "a cat in the tree."},
    {"sentence": "any wonder in the child."},
    {"sentence": "a bus in the tree."},
    {"sentence": "any honesty in the conversation."},
    {"sentence": "a cat in the closet."},
    {"sentence": "a cat under the table."},
    {"sentence": "any butter on the bread."},
    {"sentence": "a dog in the garden."},
    {"sentence": "a lamp on the floor."},
    {"sentence": "a book on the shelf."},
    {"sentence": "a dog in the washing machine."},
    {"sentence": "a computer in the office."},
    {"sentence": "any happiness in the family."},
    {"sentence": "a tree inside the house."},
    {"sentence": "a teacher in the office."},
    {"sentence": "a dog on the bus."},
    {"sentence": "any fruit in the basket."},
    {"sentence": "any strength in the bodybuilder."},
    {"sentence": "any technology in the device."},
    {"sentence": "a dog on the computer."},
    {"sentence": "a picture above the sofa."},
    {"sentence": "a chair in the corner."},
    {"sentence": "a flower in the vase."},
    {"sentence": "a clock in the living room."},
    {"sentence": "any ice in the freezer."},
    {"sentence": "any precision in the surgeon."},
    {"sentence": "a cat on the moon."},
    {"sentence": "a tree in the courtyard."},
    {"sentence": "a mirror on the floor."},
    {"sentence": "a TV in the cafe."},
    {"sentence": "any courage in the soldier."},
    {"sentence": "any endurance in the marathoner."},
    {"sentence": "a picture on the moon."},
    {"sentence": "a cat on the fence."}
  ],
  "positivePlural": [
    {"sentence": "two cars in front of the house."},
    {"sentence": "some chairs in the room."},
    {"sentence": "many cars on the street."},
    {"sentence": "some birds in the sky."},
    {"sentence": "many students in the classroom."},
    {"sentence": "many people playing frisbee in the grassy field."},
    {"sentence": "several paddleboards available for rent by the lake."},
    {"sentence": "many people watching the street performers juggle."},
    {"sentence": "many people participating in the community cleanup event."},
    {"sentence": "many flowers in the vase."},
    {"sentence": "many people participating in the charity run event."},
    {"sentence": "three cats on the sofa."},
    {"sentence": "some socks on the bed."},
    {"sentence": "some apples in the fridge."},
    {"sentence": "many trees in the forest."},
    {"sentence": "some oranges in the bowl."},
    {"sentence": "some apples in the bowl."},
    {"sentence": "some socks under the bed."},
    {"sentence": "some cookies in the jar."},
    {"sentence": "many people on the beach."},
    {"sentence": "many fish in the lake."},
    {"sentence": "many rock climbers scaling the indoor climbing wall."},
    {"sentence": "some birds in the tree."},
    {"sentence": "many people at the station."},
    {"sentence": "many fireflies twinkling in the evening sky."},
    {"sentence": "many birds in the park."},
    {"sentence": "many people at the party."},
    {"sentence": "many people attending the outdoor art class."},
    {"sentence": "many cars in the garage."},
    {"sentence": "many cars on the road."},
    {"sentence": "several canoes lined up for the upcoming race."},
    {"sentence": "many trees on the street."},
    {"sentence": "many cars in the parking lot."},
    {"sentence": "many flowers in the garden."},
    {"sentence": "several gondolas slowly moving through the narrow canals."},
    {"sentence": "several gondolas floating on the canal at sunset."},
    {"sentence": "five chairs around the table."},
    {"sentence": "some toys in the box."},
    {"sentence": "many birds in the tree."},
    {"sentence": "some chairs around the table."},
    {"sentence": "many people enjoying the interactive science exhibits."},
    {"sentence": "many stars at night."},
    {"sentence": "many clouds in the sky."},
    {"sentence": "some pencils in the box."},
    {"sentence": "some books in the bag."},
    {"sentence": "many stars in the sky."},
    {"sentence": "several paddleboards gliding across the calm bay."},
    {"sentence": "several canoes gliding across the misty lake."},
    {"sentence": "many people enjoying the live music in the town square."},
    {"sentence": "many shops in the town."},
    {"sentence": "many people in the park."},
    {"sentence": "many people enjoying the live jazz in the courtyard."},
    {"sentence": "some birds on the roof."},
    {"sentence": "many seashells scattered along the beach."},
    {"sentence": "many people enjoying the interactive art installation."},
    {"sentence": "several food carts selling local snacks in the park."},
    {"sentence": "some plates in the sink."},
    {"sentence": "many people participating in the community mural painting."},
    {"sentence": "many butterflies fluttering around the flower garden."},
    {"sentence": "several food carts selling artisanal ice cream flavors."},
    {"sentence": "some flowers in the garden."},
    {"sentence": "many children in the school."},
    {"sentence": "some fish in the pond."},
    {"sentence": "many people watching the street magic show."},
    {"sentence": "many people in the restaurant."},
    {"sentence": "many seashells arranged in artistic patterns on the beach."},
    {"sentence": "many cars in the lot."},
    {"sentence": "some books on the shelf."},
    {"sentence": "many children flying colorful kites in the open field."},
    {"sentence": "many students in the hall."},
    {"sentence": "some plates on the shelf."},
    {"sentence": "some plates on the table."},
    {"sentence": "many fish in the river."},
    {
      "sentence": "several food stalls selling traditional dishes at the market."
    },
    {"sentence": "many trees by the lake."},
    {"sentence": "several food stalls offering international street food."},
    {"sentence": "many people at the park."},
    {"sentence": "many leaves on the ground."},
    {"sentence": "many people in the class."},
    {"sentence": "some toys on the shelf."},
    {"sentence": "several food trucks offering fusion cuisine in the lot."},
    {"sentence": "several canoes paddling down the gentle river."},
    {"sentence": "some flowers in the vase."},
    {"sentence": "some socks in the drawer."},
    {"sentence": "several food trucks parked near the office complex."},
    {"sentence": "many stars in the night sky."},
    {"sentence": "many people watching the fireworks display from the beach."},
    {"sentence": "some pens on the desk."},
    {"sentence": "many people participating in the outdoor pilates class."},
    {"sentence": "some pens in the pencil case."},
    {"sentence": "several zip lines stretching between the tall trees."},
    {"sentence": "many birds in the sky."},
    {"sentence": "several hammocks set up for relaxation in the resort."},
    {
      "sentence": "several food vendors selling regional specialties at the county fair."
    },
    {"sentence": "many students in the school."},
    {"sentence": "some pencils in the case."},
    {"sentence": "several kayaks lined up on the riverbank."},
    {"sentence": "some bananas in the basket."},
    {"sentence": "several food trucks serving gourmet burgers in the square."},
    {"sentence": "some glasses on the table."},
    {"sentence": "several hot air balloons floating over the countryside."},
    {"sentence": "some bananas on the counter."},
    {"sentence": "some pens in the case."},
    {"sentence": "many houses on the hill."},
    {"sentence": "many fish in the aquarium."},
    {"sentence": "several murals depicting local legends on the city walls."},
    {"sentence": "some apples on the tree."},
    {"sentence": "some keys on the table."},
    {"sentence": "several gondolas decorated with flowers for the festival."},
    {"sentence": "some cups in the sink."},
    {"sentence": "many houses on the street."},
    {"sentence": "some toys on the floor."},
    {"sentence": "many fish in the pond."},
    {"sentence": "some clouds in the sky."},
    {"sentence": "several food trucks parked outside the music venue."},
    {"sentence": "many people participating in the sand sculpture contest."},
    {"sentence": "several rowboats tied to the dock on the lake."},
    {
      "sentence": "several food stalls selling international cuisine at the festival."
    },
    {"sentence": "many students in the class."},
    {"sentence": "some eggs on the plate."},
    {"sentence": "many books in the library."},
    {"sentence": "many shops in the mall."},
    {"sentence": "some glasses on the shelf."},
    {"sentence": "several hammocks swinging between the palm trees."},
    {"sentence": "many flowers in the field."},
    {"sentence": "many children flying kites on the windy hilltop."},
    {"sentence": "many people taking photos of the cherry blossoms."},
    {"sentence": "many books in the bag."},
    {"sentence": "some shoes by the door."},
    {"sentence": "many birds on the beach."},
    {"sentence": "some shoes in the closet."},
    {"sentence": "some glasses in the sink."},
    {"sentence": "some pencils on the desk."},
    {"sentence": "many trees in the park."},
    {"sentence": "some crayons on the floor."},
    {"sentence": "many fish in the sea."},
    {"sentence": "several kayaks navigating through the mangrove forest."},
    {"sentence": "some chairs in the garden."},
    {"sentence": "some plates in the kitchen."},
    {"sentence": "many trees in the garden."},
    {
      "sentence": "many people participating in the outdoor salsa dancing lesson."
    },
    {"sentence": "some children in the playground."},
    {"sentence": "many people participating in the outdoor yoga class."},
    {"sentence": "many trees on the hill."},
    {"sentence": "several paddle boarders enjoying the calm lake waters."},
    {"sentence": "many people at the beach."},
    {"sentence": "some bananas on the table."},
    {"sentence": "some cups in the cupboard."},
    {"sentence": "many people watching the street mime perform."},
    {"sentence": "many birds on the roof."},
    {"sentence": "some apples in the basket."},
    {"sentence": "some eggs in the basket."},
    {"sentence": "many people participating in the community garden project."},
    {
      "sentence": "several food vendors selling ethnic cuisine at the cultural fair."
    },
    {"sentence": "many people at the bus stop."},
    {"sentence": "many people enjoying the outdoor film festival."},
    {"sentence": "some bananas in the bowl."},
    {"sentence": "many people browsing the art gallery exhibition."},
    {
      "sentence": "many fireflies creating a magical atmosphere in the evening."
    },
    {"sentence": "many people admiring the sculptures in the art park."},
    {"sentence": "many people in the shop."},
    {
      "sentence": "several food vendors selling street food at the night bazaar."
    },
    {"sentence": "some books on the floor."},
    {"sentence": "many books on the shelf."},
    {"sentence": "several hot air balloons preparing for takeoff."},
    {"sentence": "many toys in the box."},
    {"sentence": "several kayaks participating in a guided eco-tour."},
    {"sentence": "several murals painted on the walls of the subway station."},
    {"sentence": "some plates in the cabinet."},
    {"sentence": "many people participating in the community drum circle."},
    {"sentence": "several paddleboats shaped like swans on the pond."},
    {"sentence": "many people taking photos of the autumn foliage."},
    {"sentence": "many people ice skating on the frozen pond."},
    {"sentence": "some eggs in the fridge."},
    {"sentence": "some shoes under the bed."},
    {"sentence": "many people enjoying the outdoor symphony performance."}
  ],
  "positiveSingular": [
    {"sentence": "some ash in the fireplace."},
    {"sentence": "a small waterfall flowing into a natural swimming hole."},
    {"sentence": "some talent in the musician."},
    {"sentence": "a small observatory on the roof of the science center."},
    {"sentence": "a man in the car."},
    {"sentence": "a little music in the concert."},
    {"sentence": "some calm in the morning."},
    {"sentence": "a beautiful ice sculpture display in the winter festival."},
    {"sentence": "a small petting zoo at the children's farm."},
    {"sentence": "a little echo in the tunnel."},
    {"sentence": "a large outdoor movie screen set up for the summer cinema."},
    {"sentence": "a cup in the sink."},
    {"sentence": "a cat on the window."},
    {"sentence": "some dryness in the desert."},
    {"sentence": "a lamp next to the bed."},
    {"sentence": "a woman at the door."},
    {"sentence": "a small orchard with a pick-your-own fruit program."},
    {"sentence": "a clock in the living room."},
    {"sentence": "a small petting zoo with farm animals at the fair."},
    {"sentence": "a cake in the fridge."},
    {"sentence": "a bird in the cage."},
    {"sentence": "a bus stop near the school."},
    {"sentence": "a little snow in the mountains."},
    {"sentence": "a little sand on the beach."},
    {"sentence": "a small observatory dome on the university campus."},
    {"sentence": "a small lighthouse at the end of the pier."},
    {"sentence": "a little faith in the belief."},
    {"sentence": "a large mural depicting local history on the city hall."},
    {"sentence": "a cup of tea by the bed."},
    {"sentence": "a woman on the phone."},
    {"sentence": "a woman in the shop."},
    {"sentence": "a red book on the table."},
    {"sentence": "a large mosaic depicting marine life on the aquarium wall."},
    {"sentence": "a little chatter in the cafeteria."},
    {"sentence": "a small lighthouse keeper's museum on the coast."},
    {"sentence": "some information on the internet."},
    {"sentence": "a man in the office."},
    {"sentence": "a bus on the street."},
    {"sentence": "a beautiful wildflower meadow next to the hiking trail."},
    {"sentence": "a little surprise in the party."},
    {"sentence": "a little light in the hallway."},
    {"sentence": "a clock on the shelf."},
    {"sentence": "a large outdoor stage set up for the summer concert series."},
    {"sentence": "some mist in the morning."},
    {"sentence": "some mystery in the novel."},
    {"sentence": "some truth in the statement."},
    {"sentence": "a book under the pillow."},
    {"sentence": "a beautiful topiary garden shaped like famous landmarks."},
    {"sentence": "some joy in the celebration."},
    {"sentence": "a little wind in the air."},
    {"sentence": "a little energy in the crowd."},
    {"sentence": "a little skill in the craftsman."},
    {"sentence": "a ball in the garden."},
    {"sentence": "a book under the bed."},
    {"sentence": "a bottle of water in the fridge."},
    {"sentence": "a beautiful butterfly garden next to the conservatory."},
    {
      "sentence": "a beautiful ice rink in the center of the shopping district."
    },
    {"sentence": "a little power in the engine."},
    {"sentence": "a woman in the car."},
    {"sentence": "a cup on the table."},
    {"sentence": "a little flour in the bowl."},
    {"sentence": "a cup on the counter."},
    {
      "sentence": "a beautiful ice bar serving cocktails in the winter village."
    },
    {"sentence": "a little intelligence in the student."},
    {"sentence": "some meat in the stew."},
    {"sentence": "some noise in the city."},
    {"sentence": "a bike near the school."},
    {"sentence": "a girl in the pool."},
    {"sentence": "a small waterfall feature in the hotel lobby."},
    {"sentence": "some fog in the valley."},
    {"sentence": "a tree in front of the house."},
    {"sentence": "a woman on the bus."},
    {"sentence": "a girl in the garden."},
    {"sentence": "a ball in the box."},
    {"sentence": "a teacher in the room."},
    {"sentence": "a small rooftop garden on the office building."},
    {"sentence": "a small lighthouse-shaped information kiosk at the marina."},
    {"sentence": "a ball in the yard."},
    {"sentence": "a little tension in the room."},
    {"sentence": "a little chocolate in the cake."},
    {"sentence": "a woman at the store."},
    {"sentence": "a man at the bus stop."},
    {"sentence": "a boy in the car."},
    {"sentence": "some coffee in the cup."},
    {"sentence": "a little steam in the shower."},
    {"sentence": "a cozy igloo hotel in the snowy landscape."},
    {"sentence": "some shadow under the tree."},
    {"sentence": "a beautiful rock garden with a raking demonstration."},
    {"sentence": "a little cold in the winter."},
    {"sentence": "a sandwich on the plate."},
    {"sentence": "a large sundial made of colorful flowers in the park."},
    {"sentence": "a cozy reading nook with bean bags in the school library."},
    {"sentence": "a lamp on the desk."},
    {"sentence": "a cup on the desk."},
    {"sentence": "a boy in the pool."},
    {"sentence": "a little pollen in the air."},
    {"sentence": "a cozy cafe with a book exchange shelf."},
    {"sentence": "a TV in the living room."},
    {"sentence": "a boy on the swing."},
    {"sentence": "a boy in the playground."},
    {"sentence": "a large sundial in the center of the rose garden."},
    {"sentence": "a little salad in the bowl."},
    {"sentence": "a computer in the office."},
    {"sentence": "a boy at the window."},
    {"sentence": "a dog in the car."},
    {"sentence": "a small chapel with stained glass windows on the hill."},
    {"sentence": "some pasta in the pot."},
    {"sentence": "a cat in the window."},
    {"sentence": "a beautiful butterfly atrium in the nature center."},
    {"sentence": "a dog by the fence."},
    {"sentence": "some research in the university."},
    {"sentence": "a pen on the desk."},
    {"sentence": "some sound in the headphones."},
    {"sentence": "a woman in the kitchen."},
    {"sentence": "a beautiful rock garden in the Zen monastery."},
    {"sentence": "some jam in the jar."},
    {"sentence": "a mirror in the bathroom."},
    {"sentence": "a little beauty in the nature."},
    {"sentence": "a chair by the window."},
    {"sentence": "a bus at the corner."},
    {"sentence": "some snow on the ground."},
    {"sentence": "a clock on the wall."},
    {"sentence": "a beautiful glass greenhouse filled with tropical plants."},
    {"sentence": "a light in the room."},
    {"sentence": "a beautiful mosaic fountain in the town center."},
    {"sentence": "a cup of coffee by the computer."},
    {"sentence": "a little patience in the teacher."},
    {"sentence": "a small cider mill offering fresh apple cider tastings."},
    {"sentence": "some flour on the counter."},
    {"sentence": "some milk in the fridge."},
    {"sentence": "a small dog in the garden."},
    {"sentence": "a bike by the tree."},
    {"sentence": "a little silence in the library."},
    {"sentence": "a dog on the bed."},
    {"sentence": "a cup of coffee on the table."},
    {"sentence": "a dog in the park."},
    {"sentence": "a small treehouse cafe hidden among the branches."},
    {"sentence": "a little love in the heart."},
    {"sentence": "a book on the table."},
    {"sentence": "a book in the bag."},
    {"sentence": "a boy on the slide."},
    {"sentence": "a small meditation labyrinth in the wellness center garden."},
    {"sentence": "a small vineyard on the sunny hillside."},
    {"sentence": "a little mud on the road."},
    {"sentence": "a dog on the porch."},
    {"sentence": "some sadness in the movie."},
    {"sentence": "a dog by the door."},
    {"sentence": "a little sugar on the table."},
    {"sentence": "a phone in my bag."},
    {"sentence": "a TV in the corner."},
    {"sentence": "a small lavender maze in the aromatherapy garden."},
    {"sentence": "some wisdom in the elder."},
    {"sentence": "a dog on the sofa."},
    {"sentence": "a cozy reading corner in the public library."},
    {"sentence": "a cat under the tree."},
    {"sentence": "some dedication in the volunteer."},
    {"sentence": "some dirt on the shoes."},
    {"sentence": "some warmth in the room."},
    {"sentence": "a small butterfly house filled with exotic species."},
    {"sentence": "a little friendship in the school."},
    {"sentence": "a cat on the chair."},
    {"sentence": "a little rice in the pot."},
    {"sentence": "some kindness in the gesture."},
    {"sentence": "a small butterfly and hummingbird garden by the cafe."},
    {"sentence": "some bravery in the firefighter."},
    {"sentence": "a large chessboard painted on the playground surface."},
    {"sentence": "a ball in the pool."},
    {"sentence": "a small waterfall cascading into a koi pond."},
    {"sentence": "a woman in the office."},
    {"sentence": "a woman in the garden."},
    {"sentence": "a girl on the bike."},
    {"sentence": "some dust on the shelf."},
    {"sentence": "some heat in the summer."},
    {"sentence": "a little history in the museum."},
    {"sentence": "a girl at the store."},
    {"sentence": "a cup of coffee on the counter."},
    {"sentence": "a shop on the corner."},
    {"sentence": "a girl on the swing."},
    {"sentence": "a large outdoor amphitheater built into the hillside."},
    {"sentence": "a little dew on the grass."},
    {"sentence": "a dog under the table."},
    {"sentence": "a little oil in the pan."},
    {"sentence": "a picture on the wall."},
    {"sentence": "some grass on the field."},
    {"sentence": "a girl on the phone."},
    {"sentence": "a large outdoor chess set in the retirement community."},
    {"sentence": "a small aviary with exotic birds in the zoo."},
    {"sentence": "a small planetarium dome at the science museum."},
    {"sentence": "a bird on the tree."},
    {"sentence": "some hope in the future."},
    {"sentence": "a beautiful water lily pond in the botanical gardens."},
    {"sentence": "a lamp by the bed."},
    {"sentence": "a large mural showcasing the city's diverse communities."},
    {"sentence": "a plant on the desk."},
    {"sentence": "a girl in the car."},
    {"sentence": "a man on the bike."},
    {"sentence": "a blanket on the bed."},
    {"sentence": "a small lighthouse-themed gift shop near the beach."},
    {"sentence": "some juice in the glass."},
    {"sentence": "a big tree in the park."},
    {"sentence": "a man in the kitchen."},
    {"sentence": "a dog under the chair."},
    {"sentence": "some speed in the race."},
    {"sentence": "some sunlight in the room."},
    {"sentence": "a cat on the sofa."},
    {"sentence": "a small orchard with various fruit trees behind the farm."},
    {"sentence": "a large chess board painted on the sidewalk."},
    {"sentence": "a dog in the yard."},
    {"sentence": "a cozy tea house hidden in the Japanese garden."},
    {"sentence": "a little rain outside."},
    {"sentence": "some art in the gallery."},
    {"sentence": "a map on the wall."},
    {"sentence": "a ball under the chair."},
    {"sentence": "a cozy bookshop with a cat sleeping in the window."},
    {"sentence": "a picture of a dog on the wall."},
    {"sentence": "a girl on the bus."},
    {"sentence": "a little science in the lab."},
    {"sentence": "a bike near the house."},
    {"sentence": "a beautiful mosaic pathway leading to the fountain."},
    {"sentence": "a cat under the chair."},
    {"sentence": "a little agility in the athlete."},
    {"sentence": "a ball under the bed."},
    {"sentence": "some cheese in the sandwich."},
    {"sentence": "a little honey on the toast."},
    {"sentence": "some care in the nursing home."},
    {"sentence": "a woman on the bike."},
    {"sentence": "a small herb garden on the restaurant's balcony."},
    {"sentence": "a little creativity in the artist."},
    {"sentence": "a little fish in the aquarium."},
    {"sentence": "some laughter in the park."},
    {"sentence": "a ball on the grass."},
    {"sentence": "a small herb spiral in the community garden."},
    {"sentence": "a phone on the table."},
    {"sentence": "a little peace in the countryside."},
    {"sentence": "a small apple cider press at the autumn festival."},
    {"sentence": "a cup of tea on the desk."},
    {"sentence": "a man on the bench."},
    {"sentence": "a little darkness in the cave."},
    {"sentence": "some clay in the garden."},
    {"sentence": "a bike near the fence."},
    {"sentence": "a hat on the hook."},
    {"sentence": "some tea in the teapot."},
    {"sentence": "a man at the door."},
    {"sentence": "a small chapel with a bell tower in the village square."},
    {"sentence": "a little smoke from the fire."},
    {"sentence": "a cup of tea by the chair."},
    {"sentence": "some water in the bottle."},
    {"sentence": "a cat on the fence."},
    {"sentence": "a man in the garden."},
    {"sentence": "a cat on the roof."},
    {"sentence": "a cup of tea on the table."},
    {"sentence": "a teacher in the classroom."},
    {"sentence": "a lamp in the room."},
    {"sentence": "a book on the chair."},
    {"sentence": "a little smoke in the chimney."},
    {"sentence": "some vibration from the phone."},
    {"sentence": "some soup in the bowl."},
    {"sentence": "a large outdoor movie screen inflated in the park."},
    {"sentence": "some excitement in the stadium."},
    {"sentence": "a man on the bicycle."},
    {"sentence": "a small wind chime garden creating soothing melodies."},
    {"sentence": "a clock in the kitchen."},
    {"sentence": "a ball on the roof."},
    {"sentence": "a large maze made of sunflowers in the field."},
    {"sentence": "a little humidity in the tropics."},
    {"sentence": "a man on the ladder."},
    {"sentence": "a cat in the box."},
    {"sentence": "a flag on top of the building."},
    {"sentence": "a TV in the bedroom."},
    {"sentence": "a little salt in the soup."},
    {"sentence": "a little flexibility in the gymnast."},
    {"sentence": "a book on the shelf."},
    {"sentence": "a boy on the bike."},
    {"sentence": "a large outdoor amphitheater in the city park."},
    {"sentence": "a boy at the door."},
    {"sentence": "some wonder in the child."},
    {"sentence": "a beautiful topiary garden shaped like animals."},
    {"sentence": "a little honesty in the conversation."},
    {"sentence": "a book on the bed."},
    {"sentence": "a bus at the stop."},
    {"sentence": "some butter on the bread."},
    {"sentence": "a girl at the window."},
    {"sentence": "a large sundial made of hedges in the formal garden."},
    {"sentence": "a ball under the table."},
    {"sentence": "a girl on the slide."},
    {"sentence": "a cup of coffee on the desk."},
    {"sentence": "a little happiness in the family."},
    {"sentence": "a tree by the house."},
    {"sentence": "a small tea ceremony house in the Japanese garden."},
    {"sentence": "a key under the mat."},
    {"sentence": "some fruit in the basket."},
    {"sentence": "some strength in the bodybuilder."},
    {"sentence": "a little technology in the device."},
    {"sentence": "a lamp in the corner."},
    {"sentence": "a small butterfly sanctuary next to the botanical garden."},
    {"sentence": "a car in the garage."},
    {"sentence": "a lamp on the table."},
    {"sentence": "a cat under the bed."},
    {"sentence": "some ice in the freezer."},
    {"sentence": "some precision in the surgeon."},
    {"sentence": "a boy on the skateboard."},
    {"sentence": "a teacher at the board."},
    {"sentence": "a man on the phone."},
    {"sentence": "a TV on the table."},
    {"sentence": "a little courage in the soldier."},
    {"sentence": "some endurance in the marathoner."},
    {"sentence": "a small lavender field next to the country road."},
    {"sentence": "a boy on the phone."}
  ]
}
